nptyping2/__init__.py
nptyping2-0.0.0.dist-info/LICENSE
nptyping2-0.0.0.dist-info/METADATA
nptyping2-0.0.0.dist-info/WHEEL
nptyping2-0.0.0.dist-info/RECORD
