Metadata-Version: 2.1
Name: nptyping2
Version: 0.0.0
Summary: nptyping updated for PEP 646
License: MIT
Author: sneakers-the-rat
Author-email: sneakers-the-rat@protonmail.com
Requires-Python: >=3.11,<4.0
Classifier: License :: OSI Approved :: MIT License
Classifier: Programming Language :: Python :: 3
Classifier: Programming Language :: Python :: 3.11
